[
    {
        "test_loss": 0.4480948746204376,
        "test_rouge1": 0.5746621238779863,
        "test_rouge2": 0.3216197272096876,
        "test_rougeL": 0.3949482315972517,
        "test_rougeLsum": 0.39489580468195806,
        "test_runtime": 74.0216,
        "test_samples_per_second": 4.607,
        "test_steps_per_second": 0.392
    },
    {
        "bleu": 0.22890141518429255,
        "precisions": [
            0.540579145565511,
            0.279861894960494,
            0.16779891304347827,
            0.10814382084985048
        ],
        "brevity_penalty": 1.0,
        "length_ratio": 1.102189781021898,
        "translation_length": 15402,
        "reference_length": 13974
    },
    {
        "google_bleu": 0.2583190394511149
    },
    {
        "meteor": 0.4963787687304395
    },
    {
        "Bert_Score": {
            "precision": 0.8391670600410082,
            "recall": 0.8674392653001018,
            "f1": 0.8525729153163272
        }
    },
    {
        "bleurt_score": 0.5523591796673638
    },
    {
        "PARENT": {
            "precision": 0.3096740239534041,
            "recall": 0.32310917200214523,
            "f_score": 0.2858390257799493
        }
    },
    {
        "time(s)": 427.1666123867035
    },
    {
        "gpu": 21330
    }
]