[
    {
        "typeKG": "Subclasses_KG"
    },
    {
        "hyper_Params": [
            0.0005,
            2,
            3
        ]
    },
    {
        "test_loss": 0.5867246389389038,
        "test_rouge1": 0.21297806610004977,
        "test_rouge2": 0.03244792075169068,
        "test_rougeL": 0.142608435333052,
        "test_rougeLsum": 0.14255435760463797,
        "test_runtime": 77.3452,
        "test_samples_per_second": 4.318,
        "test_steps_per_second": 0.543
    },
    {
        "bleu": 0.02736034728895815,
        "precisions": [
            0.2126698982986408,
            0.031485416264245704,
            0.012515951703151075,
            0.006686626746506986
        ],
        "brevity_penalty": 1.0,
        "length_ratio": 1.5358003065469674,
        "translation_length": 21042,
        "reference_length": 13701
    },
    {
        "google_bleu": 0.0664642375168691
    },
    {
        "meteor": 0.15293121182437097
    },
    {
        "Bert_Score": {
            "precision": 0.6482399286267286,
            "recall": 0.6726787809483306,
            "f1": 0.6600043222218931
        }
    },
    {
        "bleurt_score": 0.32240390545593767
    },
    {
        "time(s)": 493.71186995506287
    },
    {
        "gpu": 16044
    }
]