[
    {
        "test_loss": 7.160568714141846,
        "test_rouge1": 0.13408563939161694,
        "test_rouge2": 0.00908055672868442,
        "test_rougeL": 0.07352373975956661,
        "test_rougeLsum": 0.07364809743923906,
        "test_runtime": 696.5973,
        "test_samples_per_second": 0.49,
        "test_steps_per_second": 0.062
    },
    {
        "bleu": 0.0013830626066969674,
        "precisions": [
            0.08115278648376799,
            0.008277418031586041,
            0.0003680963529013354,
            1.4798153190481828e-05
        ],
        "brevity_penalty": 1.0,
        "length_ratio": 4.909045369972807,
        "translation_length": 68599,
        "reference_length": 13974
    },
    {
        "google_bleu": 0.022605299287114466
    },
    {
        "meteor": 0.14493738172922252
    },
    {
        "Bert_Score": {
            "precision": 0.6019141499248069,
            "recall": 0.6591476362821294,
            "f1": 0.6287607052459045
        }
    },
    {
        "bleurt_score": 0.26170635009266413
    },
    {
        "PARENT": {
            "precision": 0.05291583043458945,
            "recall": 0.00887229598955757,
            "f_score": 0.013620023922455341
        }
    },
    {
        "time(s)": 2172.6774139404297
    },
    {
        "gpu": 19420
    }
]